sample/__init__.py
sample/student.py
Student-0.0.1.dist-info/LICENSE
Student-0.0.1.dist-info/METADATA
Student-0.0.1.dist-info/WHEEL
Student-0.0.1.dist-info/top_level.txt
Student-0.0.1.dist-info/RECORD
