Metadata-Version: 2.1
Name: Student
Version: 0.0.1
Summary: student information package
Home-page: UNKNOWN
Author: sagar gajul
Author-email: gajulsagar41@gmail.com
License: UNKNOWN
Platform: UNKNOWN
Classifier: Programming Language :: Python :: 3
Classifier: License :: OSI Approved :: MIT License
Classifier: Operating System :: OS Independent
Requires-Python: >=3.6
